django_rest_exception_handler/__init__.py
django_rest_exception_handler/exception_handlers.py
django_rest_exception_handler/utils.py
django_rest_exception_handler-1.1.dist-info/LICENSE
django_rest_exception_handler-1.1.dist-info/METADATA
django_rest_exception_handler-1.1.dist-info/WHEEL
django_rest_exception_handler-1.1.dist-info/top_level.txt
django_rest_exception_handler-1.1.dist-info/RECORD
