Metadata-Version: 2.1
Name: django-rest-exception-handler
Version: 1.1
Summary: The Django REST Framework Exception Handler is a Python package designed to streamline exception handling within Django REST Framework applications. It ensures a consistent format for error responses by structuring them in a predefined JSON format.
Home-page: https://github.com/joe-philip/django_rest_exception_handler.git
Author: Joe Philip
Author-email: joe.philip@hotmail.co.in
License: MIT License
Platform: UNKNOWN
Classifier: Environment :: Web Environment
Classifier: Framework :: Django
Classifier: Intended Audience :: Developers
Classifier: License :: OSI Approved :: MIT License
Classifier: Operating System :: OS Independent
Classifier: Programming Language :: Python
Classifier: Topic :: Internet :: WWW/HTTP
Classifier: Topic :: Software Development :: Libraries :: Application Frameworks
Requires-Dist: djangorestframework >=3.14.0
Requires-Dist: toml
